bin/__init__.py
bin/ceajenkins.py
bin/create-changelog.py
bin/create_trace_graphviz.py
bin/scenariocompare.py
bin/test_substation_calc_hex_cooling.py
bin/test_substation_calc_hex_heating.py
cea/__init__.py
cea/api.py
cea/config.py
cea/constants.py
cea/default.config
cea/glossary.py
cea/inputlocator.py
cea/plugin.py
cea/schemas.py
cea/schemas.yml
cea/scripts.py
cea/scripts.yml
cea/worker.py
cea/analysis/__init__.py
cea/analysis/costs/__init__.py
cea/analysis/costs/equations.py
cea/analysis/costs/system_costs.py
cea/analysis/lca/__init__.py
cea/analysis/lca/embodied.py
cea/analysis/lca/main.py
cea/analysis/lca/operation.py
cea/analysis/multicriteria/__init__.py
cea/analysis/multicriteria/main.py
cea/databases/__init__.py
cea/databases/CH/archetypes/CONSTRUCTION_STANDARD.xlsx
cea/databases/CH/archetypes/use_types/COOLROOM.csv
cea/databases/CH/archetypes/use_types/FOODSTORE.csv
cea/databases/CH/archetypes/use_types/GYM.csv
cea/databases/CH/archetypes/use_types/HOSPITAL.csv
cea/databases/CH/archetypes/use_types/HOTEL.csv
cea/databases/CH/archetypes/use_types/INDUSTRIAL.csv
cea/databases/CH/archetypes/use_types/LAB.csv
cea/databases/CH/archetypes/use_types/LIBRARY.csv
cea/databases/CH/archetypes/use_types/MULTI_RES.csv
cea/databases/CH/archetypes/use_types/MUSEUM.csv
cea/databases/CH/archetypes/use_types/OFFICE.csv
cea/databases/CH/archetypes/use_types/PARKING.csv
cea/databases/CH/archetypes/use_types/RESTAURANT.csv
cea/databases/CH/archetypes/use_types/RETAIL.csv
cea/databases/CH/archetypes/use_types/SCHOOL.csv
cea/databases/CH/archetypes/use_types/SERVERROOM.csv
cea/databases/CH/archetypes/use_types/SINGLE_RES.csv
cea/databases/CH/archetypes/use_types/SWIMMING.csv
cea/databases/CH/archetypes/use_types/UNIVERSITY.csv
cea/databases/CH/archetypes/use_types/USE_TYPE_PROPERTIES.xlsx
cea/databases/CH/archetypes/use_types/schedule_references.txt
cea/databases/CH/assemblies/ENVELOPE.xls
cea/databases/CH/assemblies/HVAC.xls
cea/databases/CH/assemblies/SUPPLY.xls
cityenergyanalyst-3.11.0.dist-info/LICENSE
cityenergyanalyst-3.11.0.dist-info/METADATA
cityenergyanalyst-3.11.0.dist-info/WHEEL
cityenergyanalyst-3.11.0.dist-info/entry_points.txt
cityenergyanalyst-3.11.0.dist-info/top_level.txt
cityenergyanalyst-3.11.0.dist-info/RECORD
