Metadata-Version: 2.1
Name: cityenergyanalyst
Version: 3.11.0
Summary: City Energy Analyst
Home-page: http://cityenergyanalyst.com
Author: Architecture and Building Systems
Author-email: cea@arch.ethz.ch
License: MIT
Platform: UNKNOWN
Requires-Dist: SALib
Requires-Dist: cufflinks
Requires-Dist: deap
Requires-Dist: ephem
Requires-Dist: flask-restplus
Requires-Dist: flask-socketio
Requires-Dist: future
Requires-Dist: geopandas
Requires-Dist: gevent
Requires-Dist: ipython
Requires-Dist: mock
Requires-Dist: numba
Requires-Dist: openpyxl
Requires-Dist: osmnx
Requires-Dist: plotly
Requires-Dist: psutil
Requires-Dist: py4design-cea
Requires-Dist: pymc3
Requires-Dist: pysal
Requires-Dist: pyyaml
Requires-Dist: requests
Requires-Dist: seaborn
Requires-Dist: setuptools
Requires-Dist: sphinx
Requires-Dist: staticmap
Requires-Dist: sympy
Requires-Dist: timezonefinder
Requires-Dist: twine
Requires-Dist: utm
Requires-Dist: wntr
Requires-Dist: xlrd
Requires-Dist: xlwt
